cubicweb_subprocess/__init__.py
cubicweb_subprocess/__pkginfo__.py
cubicweb_subprocess/entities.py
cubicweb_subprocess/error.py
cubicweb_subprocess/hooks.py
cubicweb_subprocess/schema.py
cubicweb_subprocess/setup.py
cubicweb_subprocess/uiprops.py
cubicweb_subprocess/utils.py
cubicweb_subprocess/workflows.py
cubicweb_subprocess/data/cubes.subprocess.css
cubicweb_subprocess/data/cubes.subprocess.js
cubicweb_subprocess/i18n/en.po
cubicweb_subprocess/i18n/es.po
cubicweb_subprocess/i18n/fr.po
cubicweb_subprocess/migration/0.3.0_Any.py
cubicweb_subprocess/migration/postcreate.py
cubicweb_subprocess/views/__init__.py
cubicweb_subprocess/views/formwidgets.py
cubicweb_subprocess/views/uicfg.py
cubicweb_subprocess-1.3.0.dist-info/METADATA
cubicweb_subprocess-1.3.0.dist-info/WHEEL
cubicweb_subprocess-1.3.0.dist-info/entry_points.txt
cubicweb_subprocess-1.3.0.dist-info/top_level.txt
cubicweb_subprocess-1.3.0.dist-info/RECORD
